{
    "AWSTemplateFormatVersion": "2010-09-09",
    "Parameters": {
        "DomainName": {
            "Type": "String",
            "Default": "cuffney.com",
            "Description": "The domain name for the hosted zone"
        },
        "SSMNamespace": {
            "Type": "String",
            "Default": "/cuffney/main/hosted-zone",
            "Description": "The SSM Namespace"
        }
    },
    "Resources": {
        "HostedZone": {
            "Type": "AWS::Route53::HostedZone",
            "Properties": {
                "Name": {
                    "Ref": "DomainName"
                }
            }
        },
        "HostedZoneIdParameter": {
            "Type": "AWS::SSM::Parameter",
            "Properties": {
                "Name": {
                    "Fn::Join": [
                        "",
                        [
                            {
                                "Ref": "SSMNamespace"
                            },
                            "/hosted-zone-id"
                        ]
                    ]
                },
                "Type": "String",
                "Value": {
                    "Ref": "HostedZone"
                }
            }
        }
    }
}